cstrlbg.cpython-37m-x86_64-linux-gnu.so
cstrlbg-0.1.dist-info/WHEEL
cstrlbg-0.1.dist-info/top_level.txt
cstrlbg-0.1.dist-info/RECORD
cstrlbg-0.1.dist-info/METADATA
