Metadata-Version: 2.1
Name: cstrlbg
Version: 0.1
Summary: Em and LBG clustering
Author: Dmitry Lednov
Requires: pybind11
